just_jobs-2.1.0.dist-info/METADATA
just_jobs-2.1.0.dist-info/WHEEL
just_jobs-2.1.0.dist-info/licenses/LICENSE
just_jobs/__init__.py
just_jobs/broker.py
just_jobs/job_type.py
just_jobs/jobs.py
just_jobs/py.typed
just_jobs/settings.py
just_jobs/typing.py
just_jobs/utils.py
just_jobs-2.1.0.dist-info/RECORD
