Metadata-Version: 2.1
Name: just-jobs
Version: 2.1.0
Summary: A friendly and lightweight wrapper for arq.
Keywords: jobs arq tasks celery redis
Home-page: https://justjobs.thearchitector.dev
Author-Email: Elias Gabriel <me@eliasfgabriel.com>
License: BSD-3-Clause
Project-URL: Homepage, https://justjobs.thearchitector.dev
Project-URL: Documentation, https://justjobs.thearchitector.dev
Project-URL: Changelog, https://github.com/thearchitector/just-jobs/blob/main/CHANGELOG.md
Project-URL: Repository, https://github.com/thearchitector/just-jobs
Requires-Python: <4.0,>=3.7
Requires-Dist: arq>=0.25.0
Requires-Dist: colorama>=0.4.6
Requires-Dist: dill>=0.3.6
